{
  "id": "kb_034",
  "content": "在《天水市住房公积金贷款业务规程》贷款咨询与受理章节中第11条贷款额度的确定中新增对申请贷款职工的公积金账户设止付金额，额度为6个月的公积金贷款应还款额。\n目前我市住房公积金个贷率已超过85%风险警戒线，达到96.82%，为防范和控制住房公积金流动性风险，更好的保障缴存职工合法权益，保证住房公积金资金安全运行。根据《天水市住房公积金流动性风险预警管理办法》（试行）规定，决定启动住房公积金流动性风险紧缩二级预警。",
  "summary": "新增贷款职工公积金账户止付金额规定，额度为6个月贷款应还款额 天水公积金个贷率96.82%超85%警戒线，依据风险预警管理办法启动流动性风险紧缩二级预警",
  "entities": [
    "ent_个贷率",
    "ent_住房公积金流动性风险",
    "ent_公积金贷款",
    "ent_天水市住房公积金流动性风险预警管理办法",
    "ent_天水市住房公积金贷款业务规程",
    "ent_止付金额"
  ],
  "tags": [
    "个贷率",
    "二级预警",
    "新增规定",
    "止付金额",
    "流动性风险",
    "贷款业务规程",
    "贷款政策",
    "风险警戒线"
  ],
  "source": {
    "file": "天水市住房公积金管理中心关于调整部分政策的说明",
    "title": "天水市住房公积金管理中心关于调整部分政策的说明",
    "section": "",
    "line_range": ""
  },
  "quality": {
    "completeness": 0.95,
    "token_count": 63
  }
}