{
  "id": "kb_028",
  "content": "为进一步满足广大干部群众对办理公积金业务的差异化需求，提升服务满意度。自2025年3月1日起，全市住房公积金各服务大厅实行“周六不打烊”、工作日延时、预约上门等服务。现将有关事宜公告如下：\n1.“周六不打烊”服务。\n每周六上午8:30-12:00，下午2:30-6:00（法定节假日除外）。",
  "summary": "天水市住房公积金管理中心发布公告，自2025年3月1日起全市各服务大厅实行周六不打烊、工作日延时、预约上门等三项便民服务措施，并公告有关事宜; 全市各公积金服务大厅每周六上午8:30-12:00、下午2:30-6:00正常对外办公，法定节假日除外",
  "entities": [
    "ent_天水市住房公积金管理中心"
  ],
  "tags": [
    "policy"
  ],
  "source": {
    "file": "“”.html",
    "title": "全市住房公积金各服务大厅实行“周六不打烊”工作日延时预约上门等服务",
    "section": "引言",
    "line_range": "1-3"
  },
  "quality": {
    "confidence": 0.95
  }
}